icemac/__init__.py
icemac/install/__init__.py
icemac/install/addressbook/__init__.py
icemac/install/addressbook/_compat.py
icemac/install/addressbook/archive.py
icemac/install/addressbook/cmd.py
icemac/install/addressbook/conftest.py
icemac/install/addressbook/test_archive.py
icemac/install/addressbook/test_cmd.py
icemac/install/addressbook/testing.py
icemac/install/addressbook/utils.py
icemac/install/addressbook/install/__init__.py
icemac/install/addressbook/install/config.py
icemac/install/addressbook/install/install.py
icemac/install/addressbook/install/make_current.py
icemac/install/addressbook/install/test_config.py
icemac/install/addressbook/install/test_install.py
icemac/install/addressbook/install/test_make_current.py
icemac/install/addressbook/install/test_update.py
icemac/install/addressbook/install/update.py
icemac.install.addressbook-1.5.3.dist-info/LICENSE.txt
icemac.install.addressbook-1.5.3.dist-info/METADATA
icemac.install.addressbook-1.5.3.dist-info/WHEEL
icemac.install.addressbook-1.5.3.dist-info/entry_points.txt
icemac.install.addressbook-1.5.3.dist-info/top_level.txt
icemac.install.addressbook-1.5.3.dist-info/RECORD
