Metadata-Version: 2.1
Name: icemac.install.addressbook
Version: 1.5.3
Summary: Install, update and archive installations of icemac.addressbook.
Home-page: https://github.com/icemac/icemac.install.addressbook
Author: Michael Howitz
Author-email: icemac@gmx.net
License: MIT
Keywords: icemac addressbook install update archive manage
Platform: UNKNOWN
Classifier: Development Status :: 5 - Production/Stable
Classifier: Environment :: Console
Classifier: Intended Audience :: System Administrators
Classifier: License :: OSI Approved :: MIT License
Classifier: Natural Language :: English
Classifier: Operating System :: OS Independent
Classifier: Programming Language :: Python :: 2
Classifier: Programming Language :: Python :: 2.7
Classifier: Programming Language :: Python :: 2 :: Only
Classifier: Programming Language :: Python :: Implementation :: CPython
Classifier: Topic :: System :: Archiving
Classifier: Topic :: System :: Installation/Setup
Requires-Dist: archive
Requires-Dist: requests
Requires-Dist: z3c.recipe.usercrontab
Requires-Dist: zc.buildout
Requires-Dist: zc.lockfile
Requires-Dist: zope.password
Requires-Dist: zipp (<2)
Requires-Dist: configparser ; python_version < "3"
Requires-Dist: pathlib2 ; python_version < "3"
Provides-Extra: test
Requires-Dist: mock (<4) ; extra == 'test'
Requires-Dist: requests-file ; extra == 'test'
